projectx_api/__init__.py
projectx_api/client.py
projectx_api/enums.py
projectx_api/exceptions.py
projectx_api/logger.py
projectx_api/types.py
projectx_api/rest/__init__.py
projectx_api/rest/account.py
projectx_api/rest/authentication.py
projectx_api/rest/base.py
projectx_api/rest/market_data.py
projectx_api/rest/orders.py
projectx_api/rest/positions.py
projectx_api/rest/trades.py
projectx_api-0.1.0.dist-info/licenses/LICENSE
projectx_api-0.1.0.dist-info/METADATA
projectx_api-0.1.0.dist-info/WHEEL
projectx_api-0.1.0.dist-info/top_level.txt
projectx_api-0.1.0.dist-info/RECORD
