Metadata-Version: 2.4
Name: projectx-api
Version: 0.1.0
Summary: Python API Client for interacting with the ProjectX trading API
Author: Mickael Burguet
License: MIT
Project-URL: Homepage, https://github.com/rundef/projectx-api
Project-URL: Repository, https://github.com/rundef/projectx-api
Project-URL: Issues, https://github.com/rundef/projectx-api/issues
Keywords: python,rithmic
Classifier: Development Status :: 5 - Production/Stable
Classifier: Intended Audience :: Developers
Classifier: Topic :: Software Development :: Build Tools
Classifier: Programming Language :: Python :: 3
Classifier: Programming Language :: Python :: 3.10
Classifier: Programming Language :: Python :: 3.11
Classifier: Programming Language :: Python :: 3.12
Classifier: Programming Language :: Python :: 3.13
Classifier: Programming Language :: Python :: 3 :: Only
Classifier: License :: OSI Approved :: MIT License
Classifier: Operating System :: OS Independent
Requires-Python: >=3.10
License-File: LICENSE
Requires-Dist: httpx>=0.21.0
Requires-Dist: pattern_kit>=2.0.0
Requires-Dist: signalrcore>=0.9.5
Provides-Extra: dev
Requires-Dist: check-manifest; extra == "dev"
Provides-Extra: test
Requires-Dist: coverage; extra == "test"
Requires-Dist: pytest; extra == "test"
Dynamic: license-file
